odoo/addons/stock_release_channel_partner_address/README.rst
odoo/addons/stock_release_channel_partner_address/__init__.py
odoo/addons/stock_release_channel_partner_address/__manifest__.py
odoo/addons/stock_release_channel_partner_address/i18n/it.po
odoo/addons/stock_release_channel_partner_address/i18n/stock_release_channel_partner_address.pot
odoo/addons/stock_release_channel_partner_address/models/__init__.py
odoo/addons/stock_release_channel_partner_address/models/res_partner.py
odoo/addons/stock_release_channel_partner_address/models/stock_release_channel.py
odoo/addons/stock_release_channel_partner_address/readme/CONFIGURE.md
odoo/addons/stock_release_channel_partner_address/readme/CONTRIBUTORS.md
odoo/addons/stock_release_channel_partner_address/readme/CREDITS.md
odoo/addons/stock_release_channel_partner_address/readme/DESCRIPTION.md
odoo/addons/stock_release_channel_partner_address/readme/USAGE.md
odoo/addons/stock_release_channel_partner_address/static/description/icon.png
odoo/addons/stock_release_channel_partner_address/static/description/index.html
odoo/addons/stock_release_channel_partner_address/tests/__init__.py
odoo/addons/stock_release_channel_partner_address/tests/test_release_channel_partner_address.py
odoo/addons/stock_release_channel_partner_address/views/stock_release_channel.xml
odoo_addon_stock_release_channel_partner_address-18.0.1.0.1.1.dist-info/METADATA
odoo_addon_stock_release_channel_partner_address-18.0.1.0.1.1.dist-info/WHEEL
odoo_addon_stock_release_channel_partner_address-18.0.1.0.1.1.dist-info/top_level.txt
odoo_addon_stock_release_channel_partner_address-18.0.1.0.1.1.dist-info/RECORD
